{
	"info": {
		"_postman_id": "mercadona-store-management",
		"name": "Mercadona Store Management API",
		"description": "API completa para gestión de tiendas Mercadona con CRUD, reportes y datos de ejemplo (T004-T006 pobladas, T001-T003 libres para testing)",
		"schema": "https://schema.getpostman.com/json/collection/v2.1.0/collection.json"
	},
	"item": [
		{
			"name": "🏪 Tiendas",
			"item": [
				{
					"name": "Crear Tienda",
					"request": {
						"method": "POST",
						"header": [
							{
								"key": "Content-Type",
								"value": "application/json"
							}
						],
						"body": {
							"mode": "raw",
							"raw": "{\n    \"codigo\": \"T001\",\n    \"nombre\": \"Tienda Centro\"\n}"
						},
						"url": {
							"raw": "{{base_url}}/api/tiendas",
							"host": ["{{base_url}}"],
							"path": ["api", "tiendas"]
						}
					},
					"response": []
				},
				{
					"name": "Buscar Tienda por Código (Datos Ejemplo)",
					"request": {
						"method": "GET",
						"header": [],
						"url": {
							"raw": "{{base_url}}/api/tiendas/T004",
							"host": ["{{base_url}}"],
							"path": ["api", "tiendas", "T004"]
						}
					},
					"response": []
				},
				{
					"name": "Listar Todas las Tiendas",
					"request": {
						"method": "GET",
						"header": [],
						"url": {
							"raw": "{{base_url}}/api/tiendas",
							"host": ["{{base_url}}"],
							"path": ["api", "tiendas"]
						}
					},
					"response": []
				},
				{
					"name": "Buscar Tiendas por Nombre",
					"request": {
						"method": "GET",
						"header": [],
						"url": {
							"raw": "{{base_url}}/api/tiendas?nombre=Centro",
							"host": ["{{base_url}}"],
							"path": ["api", "tiendas"],
							"query": [
								{
									"key": "nombre",
									"value": "Centro"
								}
							]
						}
					},
					"response": []
				},
				{
					"name": "Actualizar Tienda (Datos Ejemplo)",
					"request": {
						"method": "PUT",
						"header": [
							{
								"key": "Content-Type",
								"value": "application/json"
							}
						],
						"body": {
							"mode": "raw",
							"raw": "{\n    \"codigo\": \"T004\",\n    \"nombre\": \"Mercadona Ronda Norte ACTUALIZADA\"\n}"
						},
						"url": {
							"raw": "{{base_url}}/api/tiendas/T004",
							"host": ["{{base_url}}"],
							"path": ["api", "tiendas", "T004"]
						}
					},
					"response": []
				},
				{
					"name": "Eliminar Tienda (Datos Ejemplo)",
					"request": {
						"method": "DELETE",
						"header": [],
						"url": {
							"raw": "{{base_url}}/api/tiendas/T005",
							"host": ["{{base_url}}"],
							"path": ["api", "tiendas", "T005"]
						}
					},
					"response": []
				}
			]
		},
		{
			"name": "👤 Trabajadores",
			"item": [
				{
					"name": "Crear Trabajador",
					"request": {
						"method": "POST",
						"header": [
							{
								"key": "Content-Type",
								"value": "application/json"
							}
						],
						"body": {
							"mode": "raw",
							"raw": "{\n    \"dni\": \"12345678Z\",\n    \"nombre\": \"Juan Perez\",\n    \"horasDisponibles\": 8,\n    \"codigoTienda\": \"T001\"\n}"
						},
						"url": {
							"raw": "{{base_url}}/api/trabajadores",
							"host": ["{{base_url}}"],
							"path": ["api", "trabajadores"]
						}
					},
					"response": []
				},
				{
					"name": "Buscar Trabajador por DNI (Datos Ejemplo)",
					"request": {
						"method": "GET",
						"header": [],
						"url": {
							"raw": "{{base_url}}/api/trabajadores/71234567A",
							"host": ["{{base_url}}"],
							"path": ["api", "trabajadores", "71234567A"]
						}
					},
					"response": []
				},
				{
					"name": "Listar Todos los Trabajadores",
					"request": {
						"method": "GET",
						"header": [],
						"url": {
							"raw": "{{base_url}}/api/trabajadores",
							"host": ["{{base_url}}"],
							"path": ["api", "trabajadores"]
						}
					},
					"response": []
				},
				{
					"name": "Trabajadores por Tienda (Datos Ejemplo)",
					"request": {
						"method": "GET",
						"header": [],
						"url": {
							"raw": "{{base_url}}/api/trabajadores?tienda=T004",
							"host": ["{{base_url}}"],
							"path": ["api", "trabajadores"],
							"query": [
								{
									"key": "tienda",
									"value": "T004"
								}
							]
						}
					},
					"response": []
				},
				{
					"name": "Trabajadores por Nombre (Datos Ejemplo)",
					"request": {
						"method": "GET",
						"header": [],
						"url": {
							"raw": "{{base_url}}/api/trabajadores?nombre=Ana",
							"host": ["{{base_url}}"],
							"path": ["api", "trabajadores"],
							"query": [
								{
									"key": "nombre",
									"value": "Ana"
								}
							]
						}
					},
					"response": []
				},
				{
					"name": "Actualizar Trabajador (Datos Ejemplo)",
					"request": {
						"method": "PUT",
						"header": [
							{
								"key": "Content-Type",
								"value": "application/json"
							}
						],
						"body": {
							"mode": "raw",
							"raw": "{\n    \"dni\": \"71234567A\",\n    \"nombre\": \"Ana López García ACTUALIZADA\",\n    \"horasDisponibles\": 6,\n    \"codigoTienda\": \"T004\"\n}"
						},
						"url": {
							"raw": "{{base_url}}/api/trabajadores/71234567A",
							"host": ["{{base_url}}"],
							"path": ["api", "trabajadores", "71234567A"]
						}
					},
					"response": []
				},
				{
					"name": "Eliminar Trabajador (Datos Ejemplo)",
					"request": {
						"method": "DELETE",
						"header": [],
						"url": {
							"raw": "{{base_url}}/api/trabajadores/X1111111R",
							"host": ["{{base_url}}"],
							"path": ["api", "trabajadores", "X1111111R"]
						}
					},
					"response": []
				}
			]
		},
		{
			"name": "🔗 Asignaciones",
			"item": [
				{
					"name": "Crear Asignación",
					"request": {
						"method": "POST",
						"header": [
							{
								"key": "Content-Type",
								"value": "application/json"
							}
						],
						"body": {
							"mode": "raw",
							"raw": "{\n    \"dniTrabajador\": \"12345678Z\",\n    \"nombreSeccion\": \"Horno\",\n    \"horasAsignadas\": 4\n}"
						},
						"url": {
							"raw": "{{base_url}}/api/asignaciones",
							"host": ["{{base_url}}"],
							"path": ["api", "asignaciones"]
						}
					},
					"response": []
				},
				{
					"name": "Asignaciones por Trabajador (Datos Ejemplo)",
					"request": {
						"method": "GET",
						"header": [],
						"url": {
							"raw": "{{base_url}}/api/asignaciones/trabajador/71234567A",
							"host": ["{{base_url}}"],
							"path": ["api", "asignaciones", "trabajador", "71234567A"]
						}
					},
					"response": []
				},
				{
					"name": "Asignaciones por Sección (Datos Ejemplo)",
					"request": {
						"method": "GET",
						"header": [],
						"url": {
							"raw": "{{base_url}}/api/asignaciones/seccion/Cajas",
							"host": ["{{base_url}}"],
							"path": ["api", "asignaciones", "seccion", "Cajas"]
						}
					},
					"response": []
				},
				{
					"name": "Asignaciones por Tienda (Datos Ejemplo)",
					"request": {
						"method": "GET",
						"header": [],
						"url": {
							"raw": "{{base_url}}/api/asignaciones/tienda/T005",
							"host": ["{{base_url}}"],
							"path": ["api", "asignaciones", "tienda", "T005"]
						}
					},
					"response": []
				},
				{
					"name": "Actualizar Horas de Asignación (Datos Ejemplo)",
					"request": {
						"method": "PUT",
						"header": [
							{
								"key": "Content-Type",
								"value": "application/json"
							}
						],
						"body": {
							"mode": "raw",
							"raw": "{\n    \"nuevasHoras\": 6\n}"
						},
						"url": {
							"raw": "{{base_url}}/api/asignaciones/trabajador/71234567A/seccion/Horno",
							"host": ["{{base_url}}"],
							"path": ["api", "asignaciones", "trabajador", "71234567A", "seccion", "Horno"]
						}
					},
					"response": []
				},
				{
					"name": "Eliminar Asignación (Datos Ejemplo)",
					"request": {
						"method": "DELETE",
						"header": [],
						"url": {
							"raw": "{{base_url}}/api/asignaciones/trabajador/77777777B/seccion/Droguería",
							"host": ["{{base_url}}"],
							"path": ["api", "asignaciones", "trabajador", "77777777B", "seccion", "Droguería"]
						}
					},
					"response": []
				}
			]
		},
		{
			"name": "📊 Reportes",
			"item": [
				{
					"name": "📊 Estado Completo de Tienda",
					"request": {
						"method": "GET",
						"header": [],
						"url": {
							"raw": "{{base_url}}/api/reportes/tienda/T005/estado",
							"host": ["{{base_url}}"],
							"path": ["api", "reportes", "tienda", "T005", "estado"]
						}
					},
					"response": []
				},
				{
					"name": "📈 Cobertura de Horas (Secciones Incompletas)",
					"request": {
						"method": "GET",
						"header": [],
						"url": {
							"raw": "{{base_url}}/api/reportes/tienda/T004/cobertura",
							"host": ["{{base_url}}"],
							"path": ["api", "reportes", "tienda", "T004", "cobertura"]
						}
					},
					"response": []
				}
			]
		},
		{
			"name": "🧪 Tests de Validación",
			"item": [
				{
					"name": "❌ Crear Tienda - Código Vacío",
					"request": {
						"method": "POST",
						"header": [
							{
								"key": "Content-Type",
								"value": "application/json"
							}
						],
						"body": {
							"mode": "raw",
							"raw": "{\n    \"codigo\": \"\",\n    \"nombre\": \"Tienda Centro\"\n}"
						},
						"url": {
							"raw": "{{base_url}}/api/tiendas",
							"host": ["{{base_url}}"],
							"path": ["api", "tiendas"]
						}
					},
					"response": []
				},
				{
					"name": "❌ Crear Trabajador - DNI Inválido",
					"request": {
						"method": "POST",
						"header": [
							{
								"key": "Content-Type",
								"value": "application/json"
							}
						],
						"body": {
							"mode": "raw",
							"raw": "{\n    \"dni\": \"12345678\",\n    \"nombre\": \"Juan Perez\",\n    \"horasDisponibles\": 8,\n    \"codigoTienda\": \"T001\"\n}"
						},
						"url": {
							"raw": "{{base_url}}/api/trabajadores",
							"host": ["{{base_url}}"],
							"path": ["api", "trabajadores"]
						}
					},
					"response": []
				},
				{
					"name": "❌ Crear Asignación - Horas Excesivas",
					"request": {
						"method": "POST",
						"header": [
							{
								"key": "Content-Type",
								"value": "application/json"
							}
						],
						"body": {
							"mode": "raw",
							"raw": "{\n    \"dniTrabajador\": \"12345678Z\",\n    \"nombreSeccion\": \"Horno\",\n    \"horasAsignadas\": 10\n}"
						},
						"url": {
							"raw": "{{base_url}}/api/asignaciones",
							"host": ["{{base_url}}"],
							"path": ["api", "asignaciones"]
						}
					},
					"response": []
				},
				{
					"name": "❌ Buscar Tienda Inexistente",
					"request": {
						"method": "GET",
						"header": [],
						"url": {
							"raw": "{{base_url}}/api/tiendas/INEXISTENTE",
							"host": ["{{base_url}}"],
							"path": ["api", "tiendas", "INEXISTENTE"]
						}
					},
					"response": []
				}
			]
		}
	],
	"variable": [
		{
			"key": "base_url",
			"value": "http://localhost:8080",
			"type": "string"
		}
	]
}
